connection/__init__.py
connection/connection.py
connection/wamp.py
wamp_connection-0.1.dist-info/DESCRIPTION.rst
wamp_connection-0.1.dist-info/METADATA
wamp_connection-0.1.dist-info/RECORD
wamp_connection-0.1.dist-info/WHEEL
wamp_connection-0.1.dist-info/metadata.json
wamp_connection-0.1.dist-info/top_level.txt
