Metadata-Version: 2.0
Name: wamp-connection
Version: 0.1
Summary: Simple to use library to handle a WAMP connection
Home-page: UNKNOWN
Author: GeorgeWilson96
Author-email: UNKNOWN
License: UNKNOWN
Platform: UNKNOWN
